scip_workflows/__init__.py
scip_workflows/_modidx.py
scip_workflows/common.py
scip_workflows/core.py
scip_workflows/masking.py
workflow/__init__.py
scip_workflows-0.1.2.dist-info/LICENSE
scip_workflows-0.1.2.dist-info/METADATA
scip_workflows-0.1.2.dist-info/WHEEL
scip_workflows-0.1.2.dist-info/entry_points.txt
scip_workflows-0.1.2.dist-info/top_level.txt
scip_workflows-0.1.2.dist-info/RECORD
