Metadata-Version: 2.1
Name: scip-workflows
Version: 0.1.2
Home-page: https://github.com/mlippeve/ehv/tree/master/
Author: Maxim Lippeveld
Author-email: maxim.lippeveld@ugent.be
License: Apache Software License 2.0
Keywords: imaging flow cytometry bioinformatics computational biology SCIP
Classifier: Development Status :: 3 - Alpha
Classifier: Intended Audience :: Developers
Classifier: Natural Language :: English
Classifier: Programming Language :: Python :: 3.7
Classifier: Programming Language :: Python :: 3.8
Classifier: Programming Language :: Python :: 3.9
Classifier: Programming Language :: Python :: 3.10
Classifier: License :: OSI Approved :: Apache Software License
Requires-Python: >=3.7
License-File: LICENSE
Requires-Dist: matplotlib
Requires-Dist: zarr
Requires-Dist: aicsimageio
Requires-Dist: aicspylibczi
Requires-Dist: scip
Requires-Dist: pyarrow
Requires-Dist: imbalanced-learn
Requires-Dist: seaborn
Requires-Dist: fcsparser
Requires-Dist: FlowUtils (==1.0.0)
Requires-Dist: scipy
Requires-Dist: scikit-learn
Requires-Dist: scikit-image
Requires-Dist: xgboost
Requires-Dist: scanpy
Requires-Dist: anndata
Requires-Dist: shap
Requires-Dist: kneed
Requires-Dist: cellpose
Requires-Dist: tqdm
Requires-Dist: igraph
Requires-Dist: leidenalg
Requires-Dist: umap-learn
Requires-Dist: pandas
Requires-Dist: geopandas
Provides-Extra: dev
Requires-Dist: build ; extra == 'dev'
Requires-Dist: twine ; extra == 'dev'
Requires-Dist: jupyterlab ; extra == 'dev'
Requires-Dist: nbdev (>=2) ; extra == 'dev'
Requires-Dist: clean-py ; extra == 'dev'
